README.md
setup.py
tempcf/AboutDialog.py
tempcf/ActionLogger.py
tempcf/Dataframe.py
tempcf/DatasetMetadata.py
tempcf/DepthConfigure.py
tempcf/EntryValidation.py
tempcf/ExportType.py
tempcf/FileTypes.py
tempcf/FilterConfigure.py
tempcf/FilterContainer.py
tempcf/FilterControl.py
tempcf/FilterList.py
tempcf/Filters.py
tempcf/GraphView.py
tempcf/HelpDialog.py
tempcf/ImportType.py
tempcf/LogParser.py
tempcf/MainToolbar.py
tempcf/MetadataDialog.py
tempcf/MetadataInputDialog.py
tempcf/Observable.py
tempcf/PopoutDialog.py
tempcf/ScrollableFrame.py
tempcf/TimeZoneConfigure.py
tempcf/ToolTip.py
tempcf/Utils.py
tempcf/_version.py
tempcf/main.py
tempcf/tester.py
tempcf.egg-info/PKG-INFO
tempcf.egg-info/SOURCES.txt
tempcf.egg-info/dependency_links.txt
tempcf.egg-info/entry_points.txt
tempcf.egg-info/requires.txt
tempcf.egg-info/top_level.txt
tempcf/assets/demo_FG2.txt
tempcf/assets/demo_GP5W.txt
tempcf/assets/permafrostnet_logo.ico
tempcf/assets/permafrostnet_logo_text.png