Metadata-Version: 2.1
Name: tempcf
Version: 0.6.7
Summary: A toolbox for flagging and cleaning ground temperature data
Home-page: UNKNOWN
Author: Nick Brown
Author-email: 
License: UNKNOWN
Project-URL: Source, https://gitlab.com/permafrostnet/permafrost-tempcf
Project-URL: Documentation, https://permafrostnet.gitlab.io/permafrost-tempcf/
Platform: UNKNOWN
Classifier: Development Status :: 4 - Beta
